cbmcodecs/__init__.py
cbmcodecs/petscii_c64en_lc.py
cbmcodecs/petscii_c64en_uc.py
cbmcodecs/petscii_vic20en_lc.py
cbmcodecs/petscii_vic20en_uc.py
cbmcodecs/screencode_c64_lc.py
cbmcodecs/screencode_c64_uc.py
cbmcodecs-0.2.0.dist-info/DESCRIPTION.rst
cbmcodecs-0.2.0.dist-info/METADATA
cbmcodecs-0.2.0.dist-info/RECORD
cbmcodecs-0.2.0.dist-info/WHEEL
cbmcodecs-0.2.0.dist-info/metadata.json
cbmcodecs-0.2.0.dist-info/top_level.txt
