Metadata-Version: 2.0
Name: cbmcodecs
Version: 0.2.0
Summary: Python codecs for PETSCII encodings
Home-page: https://github.com/dj51d/cbmcodecs
Author: Dan Johnson
Author-email: dj51d@warbirdsurvivors.com
License: GPLv2
Platform: UNKNOWN
Classifier: Development Status :: 4 - Beta
Classifier: Intended Audience :: Developers
Classifier: License :: OSI Approved :: GNU General Public License v2 (GPLv2)
Classifier: Programming Language :: Python
Classifier: Programming Language :: Python :: 3
Classifier: Topic :: Software Development :: Libraries :: Python Modules
